getsetpy/__init__.py
getsetpy/constants.py
getsetpy/database.py
getsetpy/exceptions.py
getsetpy/parrington.py
getsetpy/space.py
getsetpy-1.2.1.dist-info/LICENSE
getsetpy-1.2.1.dist-info/METADATA
getsetpy-1.2.1.dist-info/WHEEL
getsetpy-1.2.1.dist-info/top_level.txt
getsetpy-1.2.1.dist-info/RECORD
