Metadata-Version: 2.1
Name: getsetpy
Version: 1.2.1
Summary: official Python connector for GetSetDB
Home-page: https://github.com/getsetdb/getsetpy
Author: manan
Author-email: manan.yadav02@gmail.com
License: MIT
Keywords: getsetpy getsetdb connector database
Platform: UNKNOWN
Classifier: Topic :: Database
Classifier: Topic :: Database :: Front-Ends
Classifier: License :: OSI Approved :: MIT License
Classifier: Operating System :: Unix
Classifier: Programming Language :: Python :: 3.6
Classifier: Programming Language :: Python :: 3.7
Classifier: Programming Language :: Python :: 3.8
